{
  "fingerprint_id": "sha256:da99b911131e7af3c07e4591c1382a5d8153f52a67295938101051c560b5384f",
  "signature": {
    "severity": "ERROR",
    "first_seen": "2025-11-28T19:11:42.544377Z",
    "occurrence_count": 1,
    "last_seen": "2025-11-28T19:11:42.544377Z",
    "signature": {
      "error_type": "OperationFailure",
      "error_pattern": "OperationFailure: This indicates GitHub project management failed during reconciliation",
      "container_pattern": "orchestrator",
      "stack_signature": [],
      "normalized_message": "This indicates GitHub project management failed during reconciliation"
    },
    "created_at": "2025-11-28T19:11:42.544377Z",
    "impact_score": 0.0,
    "tags": [
      "OperationFailure",
      "orchestrator",
      "github"
    ],
    "updated_at": "2025-11-28T22:48:01.583257Z",
    "fingerprint_id": "sha256:da99b911131e7af3c07e4591c1382a5d8153f52a67295938101051c560b5384f",
    "investigation_status": "queued",
    "occurrences_last_hour": 1,
    "occurrences_last_day": 1,
    "sample_log_entries": [
      {
        "container_name": "clauditoreum-orchestrator-1",
        "raw_message": "2025-11-28 19:11:42,159 - services.project_monitor - ERROR - This indicates GitHub project management failed during reconciliation",
        "context": {
          "level": "ERROR",
          "logger": ""
        },
        "container_id": "d1897c5c73b35bec16be33306d47ee857421a5ae8d2846f8838c33de5890c992",
        "timestamp": "2025-11-28T19:11:42.541412Z"
      }
    ],
    "related_signatures": [],
    "status": "new"
  },
  "sample_logs": [
    {
      "container_name": "clauditoreum-orchestrator-1",
      "raw_message": "2025-11-28 19:11:42,159 - services.project_monitor - ERROR - This indicates GitHub project management failed during reconciliation",
      "context": {
        "level": "ERROR",
        "logger": ""
      },
      "container_id": "d1897c5c73b35bec16be33306d47ee857421a5ae8d2846f8838c33de5890c992",
      "timestamp": "2025-11-28T19:11:42.541412Z"
    }
  ],
  "created_at": "2025-11-28T22:52:44.303534+00:00"
}